{
    "1659e229649": {
        "backgroundType": "user",
        "backgroundX": 0,
        "backgroundY": 0,
        "backgroundWidth": -1,
        "backgroundHeight": -1,
        "useBgImage": true,
        "useBgColor": true,
        "backgroundAlpha": 100,
        "backgroundColor": "#bfcbe3"
    },
    "global": {
        "globalAutoLayerMarkEnable": true
    },
    "165a246dcdd": {
        "backgroundType": "user",
        "backgroundX": 0,
        "backgroundY": 0,
        "backgroundWidth": -1,
        "backgroundHeight": -1,
        "useBgImage": true,
        "useBgColor": true,
        "backgroundAlpha": 100,
        "backgroundColor": "#bfcbe5"
    },
    "165ad7647ff": {
        "path": "..\\resource\\scenes\\Question3Scene.ts",
        "class": "Question3Scene",
        "parentPath": ""
    },
    "165ad8e7465": {
        "path": "scenes\\Question4Scene.ts",
        "class": "Question4Scene",
        "parentPath": ""
    },
    "165ada3f3a7": {
        "path": "scenes\\Question5Scene.ts",
        "class": "Question5Scene",
        "parentPath": ""
    },
    "165adbd667c": {
        "path": "scenes\\Question6Scene.ts",
        "class": "Question6Scene",
        "parentPath": ""
    }
}